<?xml version="1.0" encoding="UTF-8"?>
<!DOCTYPE mapper PUBLIC "-//mybatis.org//DTD Mapper 3.0//EN" "http://mybatis.org/dtd/mybatis-3-mapper.dtd">
<mapper namespace="com.hqgml.sign.mapper.UserMapper">
  <resultMap id="BaseResultMap" type="com.hqgml.sign.pojo.User">
    <!--@mbg.generated generated on Sat Jan 04 20:35:43 CST 2020.-->
    <!--@Table user-->
    <id column="id" jdbcType="INTEGER" property="id" />
    <result column="name" jdbcType="VARCHAR" property="name" />
    <result column="sex" jdbcType="VARCHAR" property="sex" />
    <result column="idcard" jdbcType="INTEGER" property="idcard" />
    <result column="phone" jdbcType="INTEGER" property="phone" />
    <result column="pswd" jdbcType="VARCHAR" property="pswd" />
    <result column="address" jdbcType="VARCHAR" property="address" />
    <result column="lasttime" jdbcType="VARCHAR" property="lasttime" />
    <result column="role" jdbcType="VARCHAR" property="role" />
  </resultMap>
  <sql id="Base_Column_List">
    <!--@mbg.generated generated on Sat Jan 04 20:35:43 CST 2020.-->
    id, `name`, sex, idcard, phone, pswd, address, lasttime, `role`
  </sql>

<!--auto generated by MybatisCodeHelper on 2020-01-04-->
  <select id="findOneByName" resultMap="BaseResultMap">
    select
    <include refid="Base_Column_List" />
    from user
    where `name`=#{name,jdbcType=VARCHAR}
  </select>
</mapper>